{
  "createdAt": "2022-05-31T14:00:23.434Z",
  "updatedAt": "2022-05-31T14:00:23.000Z",
  "checkedAt": "2022-05-31T14:00:23.000Z",
  "id": 105986,
  "identifier": "18ab7a25-4f0e-4151-a8cc-1803ef7e2a73",
  "type": "manga",
  "page": "Mangadex",
  "title": "Hanitora! Shoukan Yuusha wo Hameru Honey Trap Hoi Mou",
  "url": "https://mangadex.org/title/18ab7a25-4f0e-4151-a8cc-1803ef7e2a73",
  "image": "https://uploads.mangadex.org/covers/18ab7a25-4f0e-4151-a8cc-1803ef7e2a73/7a5b240e-7f99-4579-8a67-ee5cd566f21e.jpg",
  "hentai": true,
  "sticky": false,
  "active": true,
  "actorId": null,
  "malId": null,
  "aniId": null,
  "deletedAt": null,
  "authors": [
    "Keteru (けてる)",
    "Miyashiro Sousuke"
  ],
  "Mal": null,
  "Ani": null
}