{
  "createdAt": "2021-03-18T14:33:30.000Z",
  "updatedAt": "2023-01-21T19:56:15.000Z",
  "checkedAt": "2023-01-21T19:56:15.000Z",
  "id": 66036,
  "identifier": "307926a3-12cc-49f2-8812-59caed4bb092",
  "type": "manga",
  "page": "Mangadex",
  "title": "Touhou - Shirokuro Dreams (Doujinshi)",
  "url": "https://mangadex.org/title/307926a3-12cc-49f2-8812-59caed4bb092",
  "image": "https://uploads.mangadex.org/covers/307926a3-12cc-49f2-8812-59caed4bb092/1b56576e-0e1f-4c3e-ad05-399efedd8c60.jpg",
  "hentai": false,
  "sticky": false,
  "active": true,
  "actorId": null,
  "malId": null,
  "aniId": null,
  "deletedAt": null,
  "authors": [
    "Shikushiku",
    "Amamori Weekly (Circle)"
  ],
  "Mal": null,
  "Ani": null
}