{
  "createdAt": "2023-01-03T04:00:38.227Z",
  "updatedAt": "2023-01-03T04:00:38.000Z",
  "checkedAt": "2023-01-03T04:00:38.000Z",
  "id": 120961,
  "identifier": "3cfe7c86-d4e7-445e-b63e-532187a4961e",
  "type": "manga",
  "page": "Mangadex",
  "title": "The Strange Alliance",
  "url": "https://mangadex.org/title/3cfe7c86-d4e7-445e-b63e-532187a4961e",
  "image": "https://uploads.mangadex.org/covers/3cfe7c86-d4e7-445e-b63e-532187a4961e/6702f3ee-b755-41b9-bdd8-bc5008fe7b27.png",
  "hentai": false,
  "sticky": false,
  "active": true,
  "actorId": null,
  "malId": null,
  "aniId": null,
  "deletedAt": null,
  "authors": [
    "Ishinomori Shotaro"
  ],
  "Mal": null,
  "Ani": null
}