{
  "createdAt": "2022-05-16T06:00:02.353Z",
  "updatedAt": "2022-12-31T04:30:03.000Z",
  "checkedAt": "2022-12-31T04:30:03.000Z",
  "id": 104583,
  "identifier": "5c6a79c3-3939-476b-baba-6d69918ec59f",
  "type": "manga",
  "page": "Mangadex",
  "title": "The Boy in a Girls' Academy",
  "url": "https://mangadex.org/title/5c6a79c3-3939-476b-baba-6d69918ec59f",
  "image": "https://uploads.mangadex.org/covers/5c6a79c3-3939-476b-baba-6d69918ec59f/13c653d0-e8e4-4e23-a0a9-46ce230f7bb2.png",
  "hentai": false,
  "sticky": false,
  "active": true,
  "actorId": null,
  "malId": null,
  "aniId": null,
  "deletedAt": null,
  "authors": [
    "Chen Guojian"
  ],
  "Mal": null,
  "Ani": null
}