{
  "createdAt": "2022-11-01T13:30:14.995Z",
  "updatedAt": "2022-11-01T13:30:15.000Z",
  "checkedAt": "2022-11-01T13:30:14.000Z",
  "id": 117191,
  "identifier": "6ad48a52-5fcd-44cd-ba7c-c00aef488acf",
  "type": "manga",
  "page": "Mangadex",
  "title": "Kago no Tori",
  "url": "https://mangadex.org/title/6ad48a52-5fcd-44cd-ba7c-c00aef488acf",
  "image": "https://uploads.mangadex.org/covers/6ad48a52-5fcd-44cd-ba7c-c00aef488acf/f8948000-2b0c-49e6-8a1d-d3e1abae4123.jpg",
  "hentai": false,
  "sticky": false,
  "active": true,
  "actorId": null,
  "malId": 10737,
  "aniId": 40737,
  "deletedAt": null,
  "authors": [
    "Sasaki Ayumi"
  ],
  "Mal": {
    "createdAt": "2022-11-01T13:30:07.590Z",
    "updatedAt": "2022-11-01T13:30:07.590Z",
    "checkedAt": "2022-11-01T13:30:07.000Z",
    "id": 10737,
    "type": "manga",
    "title": "Kago no Tori",
    "altTitle": [
      "籠の鳥"
    ],
    "url": "https://myanimelist.net/manga/10737/Kago_no_Tori",
    "image": "https://cdn.myanimelist.net/images/manga/2/271112.jpg",
    "category": "Manga",
    "hentai": false,
    "externalLinks": [],
    "legalLinks": [],
    "deletedAt": null,
    "authors": [
      "Sasaki, Ayumi"
    ]
  },
  "Ani": {
    "createdAt": "2022-11-01T13:30:14.989Z",
    "updatedAt": "2022-11-01T13:30:14.989Z",
    "checkedAt": "2022-11-01T13:30:14.000Z",
    "id": 40737,
    "type": "manga",
    "title": "Kago no Tori",
    "altTitle": [
      "籠の鳥",
      "Bird in a Cage",
      "Bird in the Cage",
      "Caged Bird",
      "Kagonotori"
    ],
    "url": "https://anilist.co/manga/40737",
    "image": "https://s4.anilist.co/file/anilistcdn/media/manga/cover/medium/10737.jpg",
    "category": "manga",
    "hentai": false,
    "externalLinks": [],
    "malId": 10737,
    "deletedAt": null,
    "authors": [
      "Sasaki Ayumi"
    ]
  }
}