{
  "createdAt": "2022-09-01T11:00:02.109Z",
  "updatedAt": "2022-09-01T11:00:02.000Z",
  "checkedAt": "2022-09-01T11:00:02.000Z",
  "id": 113674,
  "identifier": "78b2f8bd-7904-4a64-ab7c-4ce68efaba05",
  "type": "manga",
  "page": "Mangadex",
  "title": "Serena in Hypnotic Malice!",
  "url": "https://mangadex.org/title/78b2f8bd-7904-4a64-ab7c-4ce68efaba05",
  "image": "https://uploads.mangadex.org/covers/78b2f8bd-7904-4a64-ab7c-4ce68efaba05/1162a47b-02f0-4c72-abd6-b1af21a24345.jpg",
  "hentai": true,
  "sticky": false,
  "active": true,
  "actorId": null,
  "malId": null,
  "aniId": null,
  "deletedAt": null,
  "authors": [
    "Shizukana"
  ],
  "Mal": null,
  "Ani": null
}