{
  "createdAt": "2022-06-01T08:30:02.103Z",
  "updatedAt": "2022-06-01T08:30:03.000Z",
  "checkedAt": "2022-06-01T08:30:02.000Z",
  "id": 106052,
  "identifier": "7c9a5918-a499-4fc2-bc8b-ca8c1179b16b",
  "type": "manga",
  "page": "Mangadex",
  "title": "Hannah Nala",
  "url": "https://mangadex.org/title/7c9a5918-a499-4fc2-bc8b-ca8c1179b16b",
  "image": "https://uploads.mangadex.org/covers/7c9a5918-a499-4fc2-bc8b-ca8c1179b16b/7a1f34a2-e296-49ab-8862-3fce9f6a96d6.png",
  "hentai": false,
  "sticky": false,
  "active": true,
  "actorId": null,
  "malId": null,
  "aniId": null,
  "deletedAt": null,
  "authors": [
    "Egi Mugia"
  ],
  "Mal": null,
  "Ani": null
}