{
  "createdAt": "2020-10-12T16:08:28.000Z",
  "updatedAt": "2023-01-19T11:00:17.000Z",
  "checkedAt": "2023-01-19T11:00:17.000Z",
  "id": 12884,
  "identifier": "877aa28e-5c75-469c-84b1-4730bd321f53",
  "type": "manga",
  "page": "Mangadex",
  "title": "Moto Hagio's Age of The Beatles Oneshot",
  "url": "https://mangadex.org/title/877aa28e-5c75-469c-84b1-4730bd321f53",
  "image": "https://uploads.mangadex.org/covers/877aa28e-5c75-469c-84b1-4730bd321f53/04fbf43b-072e-499d-8839-4c8dd81e0ef2.png",
  "hentai": false,
  "sticky": false,
  "active": true,
  "actorId": null,
  "malId": null,
  "aniId": null,
  "deletedAt": null,
  "authors": [
    "Hagio Moto"
  ],
  "Mal": null,
  "Ani": null
}