{
  "createdAt": "2020-10-12T16:12:05.000Z",
  "updatedAt": "2021-12-05T13:19:37.000Z",
  "checkedAt": null,
  "id": 20677,
  "identifier": "8ca635da-e32e-4222-8d69-5435ca3b5504",
  "type": "manga",
  "page": "Mangadex",
  "title": "Otouto no Tomodachi",
  "url": "https://mangadex.org/title/8ca635da-e32e-4222-8d69-5435ca3b5504",
  "image": "https://uploads.mangadex.org/covers/8ca635da-e32e-4222-8d69-5435ca3b5504/761e6407-3d66-40c6-ae5c-41e0fcee6434.jpg",
  "hentai": true,
  "sticky": false,
  "active": true,
  "actorId": null,
  "malId": 65513,
  "aniId": 90207,
  "deletedAt": null,
  "authors": [
    "Tottototomekichi",
    "Tomekichi"
  ],
  "Mal": {
    "createdAt": "2020-10-12T15:45:08.000Z",
    "updatedAt": "2022-06-09T21:44:52.000Z",
    "checkedAt": "2022-06-09T21:44:52.000Z",
    "id": 65513,
    "type": "manga",
    "title": "Otouto no Tomodachi",
    "altTitle": [
      "おとうとのともだち"
    ],
    "url": "https://myanimelist.net/manga/65513/Otouto_no_Tomodachi",
    "image": "https://cdn.myanimelist.net/images/manga/1/112395.jpg",
    "category": "Doujinshi",
    "hentai": true,
    "externalLinks": [],
    "legalLinks": [],
    "deletedAt": null,
    "authors": [
      "Tomekichi"
    ]
  },
  "Ani": {
    "createdAt": "2022-05-13T12:52:06.967Z",
    "updatedAt": "2022-06-09T21:44:52.000Z",
    "checkedAt": "2022-06-09T21:44:52.000Z",
    "id": 90207,
    "type": "manga",
    "title": "Otouto no Tomodachi",
    "altTitle": [
      "おとうとのともだち"
    ],
    "url": "https://anilist.co/manga/90207",
    "image": "https://s4.anilist.co/file/anilistcdn/media/manga/cover/medium/90207-TqYY9VSxUCIK.jpg",
    "category": "manga",
    "hentai": true,
    "externalLinks": [],
    "malId": 65513,
    "deletedAt": null,
    "authors": [
      "Tomekichi"
    ]
  }
}