{
  "createdAt": "2022-09-20T00:30:00.512Z",
  "updatedAt": "2022-09-20T00:30:00.000Z",
  "checkedAt": "2022-09-20T00:30:00.000Z",
  "id": 114776,
  "identifier": "ac35d3d6-202a-4280-abc8-b021abd04b1a",
  "type": "manga",
  "page": "Mangadex",
  "title": "The Boy I Love's Secret Channel",
  "url": "https://mangadex.org/title/ac35d3d6-202a-4280-abc8-b021abd04b1a",
  "image": "https://uploads.mangadex.org/covers/ac35d3d6-202a-4280-abc8-b021abd04b1a/9d777a67-4a5f-4c03-865c-88e3cb592148.jpg",
  "hentai": true,
  "sticky": false,
  "active": true,
  "actorId": null,
  "malId": null,
  "aniId": null,
  "deletedAt": null,
  "authors": [
    "Chabashira Puu"
  ],
  "Mal": null,
  "Ani": null
}