{
  "createdAt": "2022-12-28T09:00:01.365Z",
  "updatedAt": "2022-12-28T09:00:01.000Z",
  "checkedAt": "2022-12-28T09:00:01.000Z",
  "id": 120593,
  "identifier": "ad5af388-78c7-4f17-a55c-62e6f2975197",
  "type": "manga",
  "page": "Mangadex",
  "title": "Seitenkango, Shinyuu to ～Aibou Hen～",
  "url": "https://mangadex.org/title/ad5af388-78c7-4f17-a55c-62e6f2975197",
  "image": "https://uploads.mangadex.org/covers/ad5af388-78c7-4f17-a55c-62e6f2975197/44e81aa2-5463-4c52-b5d1-3dea8133442f.jpg",
  "hentai": true,
  "sticky": false,
  "active": true,
  "actorId": null,
  "malId": null,
  "aniId": null,
  "deletedAt": null,
  "authors": [
    "Eroe"
  ],
  "Mal": null,
  "Ani": null
}