{
  "createdAt": "2022-07-13T07:30:07.406Z",
  "updatedAt": "2022-07-13T07:30:10.000Z",
  "checkedAt": "2022-07-13T07:30:07.000Z",
  "id": 109496,
  "identifier": "c7c33705-b3bf-48a9-ae6a-c18d35c92167",
  "type": "manga",
  "page": "Mangadex",
  "title": "Niko to Maki no Natsuyasumi",
  "url": "https://mangadex.org/title/c7c33705-b3bf-48a9-ae6a-c18d35c92167",
  "image": "https://uploads.mangadex.org/covers/c7c33705-b3bf-48a9-ae6a-c18d35c92167/4d0dfc75-2be2-4178-968c-0a63be6e89b6.jpg",
  "hentai": true,
  "sticky": false,
  "active": true,
  "actorId": null,
  "malId": null,
  "aniId": null,
  "deletedAt": null,
  "authors": [
    "number2",
    "Ohtomo Takuji"
  ],
  "Mal": null,
  "Ani": null
}