{
  "createdAt": "2020-10-12T16:10:20.000Z",
  "updatedAt": "2021-12-05T00:20:40.000Z",
  "checkedAt": null,
  "id": 16897,
  "identifier": "d90fb90c-39bb-4d43-987d-28e3cfda8fa3",
  "type": "manga",
  "page": "Mangadex",
  "title": "Lens Sou no Sankaku",
  "url": "https://mangadex.org/title/d90fb90c-39bb-4d43-987d-28e3cfda8fa3",
  "image": "https://uploads.mangadex.org/covers/d90fb90c-39bb-4d43-987d-28e3cfda8fa3/0ee003c8-9c62-418e-9c0c-710c9eb13443.jpg",
  "hentai": false,
  "sticky": false,
  "active": true,
  "actorId": null,
  "malId": 107120,
  "aniId": 99752,
  "deletedAt": null,
  "authors": [
    "Nogiri Youko"
  ],
  "Mal": {
    "createdAt": "2020-10-12T15:47:05.000Z",
    "updatedAt": "2022-05-15T00:40:41.000Z",
    "checkedAt": "2022-05-15T00:40:41.000Z",
    "id": 107120,
    "type": "manga",
    "title": "Renzu-sou no Sankaku",
    "altTitle": [
      "Lens-sou no Sankaku",
      "Love in Focus",
      "蓮住〈レンズ〉荘のさんかく"
    ],
    "url": "https://myanimelist.net/manga/107120/Renzu-sou_no_Sankaku",
    "image": "https://cdn.myanimelist.net/images/manga/1/196301.jpg",
    "category": "Manga",
    "hentai": false,
    "externalLinks": [],
    "legalLinks": [],
    "deletedAt": null,
    "authors": [
      "Nogiri, Youko"
    ]
  },
  "Ani": {
    "createdAt": "2022-05-13T12:58:43.559Z",
    "updatedAt": "2022-05-16T14:51:02.000Z",
    "checkedAt": "2022-05-16T14:51:02.000Z",
    "id": 99752,
    "type": "manga",
    "title": "Renzu-sou no Sankaku",
    "altTitle": [
      "Love in Focus",
      "蓮住荘のさんかく"
    ],
    "url": "https://anilist.co/manga/99752",
    "image": "https://s4.anilist.co/file/anilistcdn/media/manga/cover/medium/nx99752-Awqz8K2feSuC.jpg",
    "category": "manga",
    "hentai": false,
    "externalLinks": [],
    "malId": 107120,
    "deletedAt": null,
    "authors": [
      "Youko Nogiri"
    ]
  }
}