{
  "createdAt": "2022-04-25T09:01:27.000Z",
  "updatedAt": "2023-01-23T11:11:14.000Z",
  "checkedAt": "2023-01-23T11:11:14.000Z",
  "id": 102091,
  "identifier": "fafd3faf-0cd5-4e7a-bc6a-517e671e9e15",
  "type": "manga",
  "page": "Mangadex",
  "title": "Uralympic! ~Zenra No Danjo Pair De Winter Sports~",
  "url": "https://mangadex.org/title/fafd3faf-0cd5-4e7a-bc6a-517e671e9e15",
  "image": "https://uploads.mangadex.org/covers/fafd3faf-0cd5-4e7a-bc6a-517e671e9e15/6d582211-c7e0-439b-8b3a-87888ce12774.jpg",
  "hentai": true,
  "sticky": false,
  "active": true,
  "actorId": null,
  "malId": null,
  "aniId": null,
  "deletedAt": null,
  "authors": [
    "Agata"
  ],
  "Mal": null,
  "Ani": null
}