{
  "createdAt": "2020-10-12T15:38:18.000Z",
  "updatedAt": "2022-11-30T23:49:17.000Z",
  "checkedAt": "2022-11-30T23:49:17.000Z",
  "id": 1553,
  "type": "anime",
  "title": "Queen Emeraldas",
  "altTitle": [
    "クィーン・エメラルダス"
  ],
  "url": "https://myanimelist.net/anime/1553/Queen_Emeraldas",
  "image": "https://cdn.myanimelist.net/images/anime/10/21120.jpg",
  "category": "OVA",
  "hentai": false,
  "externalLinks": [
    {
      "site": "animedb",
      "url": "http://anidb.info/perl-bin/animedb.pl?show=anime&aid=683"
    },
    {
      "site": "animenewsnetwork",
      "url": "http://www.animenewsnetwork.com/encyclopedia/anime.php?id=199"
    },
    {
      "site": "wikipedia",
      "url": "http://en.wikipedia.org/wiki/Queen_Emeraldas"
    }
  ],
  "legalLinks": [],
  "deletedAt": null,
  "anidbId": 683,
  "Pages": {
    "9anime": {
      "2qoq": {
        "createdAt": "2020-10-12T15:49:30.000Z",
        "updatedAt": "2023-01-17T18:36:37.000Z",
        "checkedAt": "2023-01-17T18:36:37.000Z",
        "id": 1504,
        "identifier": "2qoq",
        "type": "anime",
        "page": "9anime",
        "title": "Queen Emeraldas",
        "url": "https://9anime.pl/watch/queen-emeraldas.2qoq",
        "image": "https://static.bunnycdn.ru/i/cache/images/2018/04/9584d86f445ddd6de181e0486c327b0f.jpg",
        "hentai": false,
        "sticky": false,
        "active": true,
        "actorId": null,
        "malId": 1553,
        "aniId": 1553,
        "deletedAt": null
      }
    },
    "Gogoanime": {
      "queen-emeraldas": {
        "createdAt": "2022-03-07T12:30:02.000Z",
        "updatedAt": "2023-01-19T19:54:43.000Z",
        "checkedAt": "2023-01-19T19:54:43.000Z",
        "id": 40409,
        "identifier": "queen-emeraldas",
        "type": "anime",
        "page": "Gogoanime",
        "title": "Queen Emeraldas",
        "url": "https://gogoanime.bid/category/queen-emeraldas",
        "image": "https://gogocdn.net/cover/queen-emeraldas.png",
        "hentai": false,
        "sticky": false,
        "active": true,
        "actorId": null,
        "malId": 1553,
        "aniId": 1553,
        "deletedAt": null
      }
    }
  }
}