{
  "createdAt": "2023-01-02T06:30:06.045Z",
  "updatedAt": "2023-01-02T06:30:06.045Z",
  "checkedAt": "2023-01-02T06:30:06.000Z",
  "id": 8294,
  "type": "anime",
  "title": "Shinshou Genmukan",
  "altTitle": [
    "真章 幻夢館"
  ],
  "url": "https://myanimelist.net/anime/8294/Shinshou_Genmukan",
  "image": "https://cdn.myanimelist.net/images/anime/7/26731.jpg",
  "category": "OVA",
  "hentai": true,
  "externalLinks": [
    {
      "site": "officialsite",
      "url": "http://chichinoya.jp/chichi/common/genmukan/index.html"
    },
    {
      "site": "anidb",
      "url": "https://anidb.net/perl-bin/animedb.pl?show=anime&aid=7309"
    },
    {
      "site": "ann",
      "url": "https://www.animenewsnetwork.com/encyclopedia/anime.php?id=11453"
    }
  ],
  "legalLinks": [],
  "deletedAt": null,
  "anidbId": 7309,
  "Pages": {}
}