{
  "createdAt": "2022-02-28T01:48:52.000Z",
  "updatedAt": "2022-02-28T01:48:52.000Z",
  "checkedAt": null,
  "id": 12934,
  "type": "manga",
  "title": "Justy",
  "altTitle": [
    "Cosmo Police Justy",
    "ジャスティ"
  ],
  "url": "https://myanimelist.net/manga/12934/Justy",
  "image": "https://cdn.myanimelist.net/images/manga/1/82700.jpg",
  "category": "Manga",
  "hentai": false,
  "externalLinks": [
    {
      "site": "wikipedia",
      "url": "http://ja.wikipedia.org/wiki/%E3%82%B8%E3%83%A3%E3%82%B9%E3%83%86%E3%82%A3_%28%E6%BC%AB%E7%94%BB%29"
    }
  ],
  "legalLinks": [],
  "deletedAt": null,
  "authors": [
    "Okazaki, Tsuguo"
  ],
  "Pages": {}
}