{
  "createdAt": "2020-10-12T15:41:59.000Z",
  "updatedAt": "2022-05-19T21:08:24.000Z",
  "checkedAt": "2022-05-19T21:08:24.000Z",
  "id": 13562,
  "type": "manga",
  "title": "Doll Star: Kotodama Tsukai Ihon",
  "altTitle": [
    "Doll Star: Invoker Variant",
    "ドールスター言霊使い異本"
  ],
  "url": "https://myanimelist.net/manga/13562/Doll_Star__Kotodama_Tsukai_Ihon",
  "image": "https://cdn.myanimelist.net/images/manga/1/19432.jpg",
  "category": "Manga",
  "hentai": false,
  "externalLinks": [],
  "legalLinks": [],
  "deletedAt": null,
  "authors": [
    "Satomi, Ran",
    "Maki, Ebishi"
  ],
  "Pages": {}
}