{
  "createdAt": "2021-10-26T03:01:15.000Z",
  "updatedAt": "2022-05-14T18:01:35.000Z",
  "checkedAt": "2022-05-14T18:01:35.000Z",
  "id": 141388,
  "type": "manga",
  "title": "Maroushinshi B.T.",
  "altTitle": [
    "Cool Shock Old B.T.",
    "魔老紳士ビーティー"
  ],
  "url": "https://myanimelist.net/manga/141388/Maroushinshi_BT",
  "image": "https://cdn.myanimelist.net/images/manga/2/251615.jpg",
  "category": "One-shot",
  "hentai": false,
  "externalLinks": [
    {
      "site": "wikipedia",
      "url": "https://ja.wikipedia.org/wiki/%E9%AD%94%E5%B0%91%E5%B9%B4%E3%83%93%E3%83%BC%E3%83%86%E3%82%A3%E3%83%BC"
    }
  ],
  "legalLinks": [],
  "deletedAt": null,
  "authors": [
    "NISIO, ISIN",
    "Demizu, Posuka"
  ],
  "Pages": {}
}