{
  "createdAt": "2022-05-24T03:30:09.115Z",
  "updatedAt": "2022-05-24T03:30:09.115Z",
  "checkedAt": "2022-05-24T03:30:09.000Z",
  "id": 147092,
  "type": "manga",
  "title": "Sasha-chan to Classmate Otaku-kun",
  "altTitle": [
    "JC Sasha and Her Otaku Classmate",
    "サーシャちゃんとクラスメイトオタクくん"
  ],
  "url": "https://myanimelist.net/manga/147092/Sasha-chan_to_Classmate_Otaku-kun",
  "image": "https://cdn.myanimelist.net/images/manga/3/260388.jpg",
  "category": "Manga",
  "hentai": false,
  "externalLinks": [
    {
      "site": "officialsite",
      "url": "https://comic-walker.com/contents/detail/KDCW_AM07202859010000_68/"
    }
  ],
  "legalLinks": [],
  "deletedAt": null,
  "authors": [
    "Haguhagu"
  ],
  "Pages": {
    "Mangadex": {
      "65d936d2-e401-4dc7-a5d6-ee9a4eaa3939": {
        "createdAt": "2022-05-01T11:01:28.000Z",
        "updatedAt": "2022-05-30T06:03:42.000Z",
        "checkedAt": "2022-05-13T15:51:11.000Z",
        "id": 102418,
        "identifier": "65d936d2-e401-4dc7-a5d6-ee9a4eaa3939",
        "type": "manga",
        "page": "Mangadex",
        "title": "JC Sasha and Her Otaku Classmate",
        "url": "https://mangadex.org/title/65d936d2-e401-4dc7-a5d6-ee9a4eaa3939",
        "image": "https://uploads.mangadex.org/covers/65d936d2-e401-4dc7-a5d6-ee9a4eaa3939/81caea9c-a7c0-4ef6-bfb7-a4157cbe123a.jpg",
        "hentai": false,
        "sticky": false,
        "active": true,
        "actorId": 1,
        "malId": 147092,
        "aniId": 138818,
        "deletedAt": null,
        "authors": [
          "Haguhagu",
          "Rinjuu Circus (Circle)"
        ]
      }
    },
    "MangaNato": {
      "manga-ny990907": {
        "createdAt": "2022-05-30T15:30:00.749Z",
        "updatedAt": "2022-05-30T16:20:00.000Z",
        "checkedAt": "2022-05-30T15:30:00.000Z",
        "id": 105887,
        "identifier": "manga-ny990907",
        "type": "manga",
        "page": "MangaNato",
        "title": "Jc Sasha And Her Otaku Classmate",
        "url": "https://manganato.com/manga-ny990907",
        "image": "https://avt.mkklcdnv6temp.com/43/s/25-1653916405.jpg",
        "hentai": false,
        "sticky": false,
        "active": true,
        "actorId": null,
        "malId": 147092,
        "aniId": 138818,
        "deletedAt": null,
        "authors": [
          "Haguhagu",
          "Rinjuu Circus (Circle)"
        ]
      }
    },
    "MangaFox": {
      "sasha_chan_to_classmate_otaku_kun": {
        "createdAt": "2022-06-08T08:30:00.458Z",
        "updatedAt": "2022-06-08T09:20:00.000Z",
        "checkedAt": "2022-06-08T08:30:00.000Z",
        "id": 106732,
        "identifier": "sasha_chan_to_classmate_otaku_kun",
        "type": "manga",
        "page": "MangaFox",
        "title": "Sasha-chan to Classmate Otaku-kun",
        "url": "https://fanfox.net/manga/sasha_chan_to_classmate_otaku_kun/",
        "image": "https://fmcdn.mfcdn.net/store/manga/42508/cover.jpg",
        "hentai": false,
        "sticky": false,
        "active": true,
        "actorId": null,
        "malId": 147092,
        "aniId": 138818,
        "deletedAt": null,
        "authors": [
          "Haguhagu"
        ]
      }
    }
  }
}