{
  "createdAt": "2021-06-03T00:32:01.000Z",
  "updatedAt": "2022-05-16T17:46:49.000Z",
  "checkedAt": "2022-05-16T17:46:49.000Z",
  "id": 1621,
  "type": "manga",
  "title": "Lodoss-tou Senki: Pharis no Seijo",
  "altTitle": [
    "Record of Lodoss War: The Lady of Pharis",
    "ロードス島戦記 ファリスの聖女"
  ],
  "url": "https://myanimelist.net/manga/1621/Lodoss-tou_Senki__Pharis_no_Seijo",
  "image": "https://cdn.myanimelist.net/images/manga/1/135807.jpg",
  "category": "Manga",
  "hentai": false,
  "externalLinks": [
    {
      "site": "wikipedia",
      "url": "http://ja.wikipedia.org/wiki/%E3%83%AD%E3%83%BC%E3%83%89%E3%82%B9%E5%B3%B6%E4%BC%9D%E8%AA%AC"
    }
  ],
  "legalLinks": [],
  "deletedAt": null,
  "authors": [
    "Mizuno, Ryou",
    "Yamada, Akihiro"
  ],
  "Pages": {
    "9anime": {
      "940q": {
        "createdAt": "2020-10-12T15:51:44.000Z",
        "updatedAt": "2021-05-20T15:21:51.000Z",
        "checkedAt": null,
        "id": 4198,
        "identifier": "940q",
        "type": "anime",
        "page": "9anime",
        "title": "Haru no Ashioto The Movie: Ourin Dakkan",
        "url": "https://9anime.to/watch/haru-no-ashioto-the-movie-ourin-dakkan-dub.940q",
        "image": "https://images2-focus-opensocial.googleusercontent.com/gadgets/proxy?container=focus&amp;gadget=a&amp;no_expand=1&amp;refresh=604800&amp;url=http://2.bp.blogspot.com/-BC1VmC5WfEQ/WKR2JzCkCZI/AAAAAAABdB0/9OS-5QhXzg4/s0/",
        "hentai": false,
        "sticky": false,
        "active": true,
        "actorId": null,
        "malId": 1621,
        "aniId": 1621,
        "deletedAt": null
      }
    }
  }
}