{
  "createdAt": "2022-05-29T04:00:10.507Z",
  "updatedAt": "2022-05-29T04:00:10.507Z",
  "checkedAt": "2022-05-29T04:00:10.000Z",
  "id": 16749,
  "type": "manga",
  "title": "Kaiki Hakubutsukan",
  "altTitle": [
    "Doll House",
    "Norou Ningyou",
    "Shinku no Kage",
    "Horror Museum",
    "怪奇博物館"
  ],
  "url": "https://myanimelist.net/manga/16749/Kaiki_Hakubutsukan",
  "image": "https://cdn.myanimelist.net/images/manga/1/24807.jpg",
  "category": "Manga",
  "hentai": false,
  "externalLinks": [],
  "legalLinks": [],
  "deletedAt": null,
  "authors": [
    "Matsumoto, Yoko",
    "Akagawa, Jirou"
  ],
  "Pages": {}
}