{
  "createdAt": "2020-10-12T15:42:31.000Z",
  "updatedAt": "2022-05-16T00:13:35.000Z",
  "checkedAt": "2022-05-16T00:13:35.000Z",
  "id": 18258,
  "type": "manga",
  "title": "Becchin to Mandara",
  "altTitle": [
    "Velveteen & Mandala",
    "べっちんとまんだら"
  ],
  "url": "https://myanimelist.net/manga/18258/Becchin_to_Mandara",
  "image": "https://cdn.myanimelist.net/images/manga/3/27905.jpg",
  "category": "Manga",
  "hentai": false,
  "externalLinks": [],
  "legalLinks": [],
  "deletedAt": null,
  "authors": [
    "Matsumoto, Jiro"
  ],
  "Pages": {}
}