{
  "createdAt": "2020-10-12T15:45:05.000Z",
  "updatedAt": "2022-05-19T19:04:55.000Z",
  "checkedAt": "2022-05-19T19:04:55.000Z",
  "id": 63555,
  "type": "manga",
  "title": "Bernard-jou Iwaku.",
  "altTitle": [
    "Miss Bernard said.",
    "バーナード嬢曰く。"
  ],
  "url": "https://myanimelist.net/manga/63555/Bernard-jou_Iwaku",
  "image": "https://cdn.myanimelist.net/images/manga/1/182407.jpg",
  "category": "Manga",
  "hentai": false,
  "externalLinks": [
    {
      "site": "wikipedia",
      "url": "https://ja.wikipedia.org/wiki/%E3%83%90%E3%83%BC%E3%83%8A%E3%83%BC%E3%83%89%E5%AC%A2%E6%9B%B0%E3%81%8F%E3%80%82"
    }
  ],
  "legalLinks": [],
  "deletedAt": null,
  "authors": [
    "Shikawa, Yuuki"
  ],
  "Pages": {}
}