{
  "createdAt": "2020-10-12T15:41:12.000Z",
  "updatedAt": "2021-12-03T01:16:48.000Z",
  "checkedAt": null,
  "id": 7049,
  "type": "manga",
  "title": "Atashi no Onna ni Te wo Dasuna",
  "altTitle": [
    "Hands Off My Girl",
    "あたしの女に手をだすな"
  ],
  "url": "https://myanimelist.net/manga/7049/Atashi_no_Onna_ni_Te_wo_Dasuna",
  "image": "https://cdn.myanimelist.net/images/manga/2/9438.jpg",
  "category": "Manga",
  "hentai": false,
  "externalLinks": [],
  "legalLinks": [],
  "deletedAt": null,
  "authors": [
    "Minami, Q-ta"
  ],
  "Pages": {}
}