{
  "createdAt": "2020-10-12T15:45:44.000Z",
  "updatedAt": "2022-06-07T22:50:46.000Z",
  "checkedAt": "2022-06-07T22:50:46.000Z",
  "id": 85989,
  "type": "manga",
  "title": "Tenshi to Akuto!!",
  "altTitle": [
    "Tenshi to Act!!",
    "Angel and Akuto!!",
    "天使とアクト!!"
  ],
  "url": "https://myanimelist.net/manga/85989/Tenshi_to_Akuto",
  "image": "https://cdn.myanimelist.net/images/manga/2/168134.jpg",
  "category": "Manga",
  "hentai": false,
  "externalLinks": [
    {
      "site": "wikipedia",
      "url": "https://ja.wikipedia.org/wiki/%E5%A4%A9%E4%BD%BF%E3%81%A8%E3%82%A2%E3%82%AF%E3%83%88!!"
    }
  ],
  "legalLinks": [],
  "deletedAt": null,
  "authors": [
    "Hirakawa, Aya"
  ],
  "Pages": {}
}