{
  "createdAt": "2022-01-20T20:12:58.000Z",
  "updatedAt": "2022-06-26T22:08:31.000Z",
  "checkedAt": "2022-06-26T22:08:31.000Z",
  "id": 104465,
  "type": "anime",
  "title": "Yi Kong Zhi Dian",
  "altTitle": [
    "Brinken: Skate Revolution",
    "翼空之巅",
    "Brinken: Finger Skate Generation"
  ],
  "url": "https://anilist.co/anime/104465",
  "image": "https://s4.anilist.co/file/anilistcdn/media/anime/cover/medium/104465-8mGEmZOwUZmO.jpg",
  "category": "tv",
  "hentai": false,
  "externalLinks": [],
  "malId": 38069,
  "deletedAt": null,
  "Pages": {
    "9anime": {
      "xrvp8": {
        "createdAt": "2022-06-04T09:30:06.800Z",
        "updatedAt": "2022-06-04T10:20:00.000Z",
        "checkedAt": "2022-06-04T09:30:06.000Z",
        "id": 41123,
        "identifier": "xrvp8",
        "type": "anime",
        "page": "9anime",
        "title": "Yi Kong Zhi Dian (Dub)",
        "url": "https://9anime.to/watch/brinken-skate-revolution-dub.xrvp8",
        "image": "https://static.bunnycdn.ru/i/cache/images/e/ea/ea93198c8324fd2c08226105879539e5.jpg",
        "hentai": false,
        "sticky": false,
        "active": true,
        "actorId": null,
        "malId": 38069,
        "aniId": 104465,
        "deletedAt": null
      }
    }
  }
}