{
  "createdAt": "2021-05-20T14:43:12.000Z",
  "updatedAt": "2022-12-02T16:33:02.000Z",
  "checkedAt": "2022-12-02T16:33:02.000Z",
  "id": 21645,
  "type": "anime",
  "title": "MARGINAL#4: KISS kara Tsukuru Big Bang",
  "altTitle": [
    "MARGINAL #4 the Animation",
    "MARGINAL#4 KISSから創造るBig Bang"
  ],
  "url": "https://anilist.co/anime/21645",
  "image": "https://s4.anilist.co/file/anilistcdn/media/anime/cover/medium/bx21645-XN8vOm2VPEbO.jpg",
  "category": "tv",
  "hentai": false,
  "externalLinks": [
    {
      "site": "Crunchyroll",
      "url": "http://www.crunchyroll.com/marginal-4-the-animation"
    }
  ],
  "malId": 33788,
  "deletedAt": null,
  "Pages": {
    "9anime": {
      "8763": {
        "createdAt": "2020-10-12T15:48:35.000Z",
        "updatedAt": "2023-01-17T15:28:16.000Z",
        "checkedAt": "2023-01-17T15:28:16.000Z",
        "id": 283,
        "identifier": "8763",
        "type": "anime",
        "page": "9anime",
        "title": "MARGINAL#4: KISS kara Tsukuru Big Bang",
        "url": "https://9anime.pl/watch/marginal-4-the-animation.8763",
        "image": "https://static.bunnycdn.ru/i/cache/images/2018/04/682a59a5fb966b1d660ce348b786e6e7.jpg",
        "hentai": false,
        "sticky": false,
        "active": true,
        "actorId": null,
        "malId": 33788,
        "aniId": 21645,
        "deletedAt": null
      }
    },
    "Gogoanime": {
      "marginal4-kiss-kara-tsukuru-big-bang": {
        "createdAt": "2020-11-21T15:22:10.000Z",
        "updatedAt": "2023-01-19T11:44:37.000Z",
        "checkedAt": "2023-01-19T11:44:37.000Z",
        "id": 29490,
        "identifier": "marginal4-kiss-kara-tsukuru-big-bang",
        "type": "anime",
        "page": "Gogoanime",
        "title": "Marginal#4: Kiss kara Tsukuru Big Bang",
        "url": "https://gogoanime.bid/category/marginal4-kiss-kara-tsukuru-big-bang",
        "image": "https://gogocdn.net/cover/marginal4-kiss-kara-tsukuru-big-bang.png",
        "hentai": false,
        "sticky": false,
        "active": true,
        "actorId": null,
        "malId": 33788,
        "aniId": 21645,
        "deletedAt": null
      }
    }
  }
}