{
  "createdAt": "2021-05-20T14:43:23.000Z",
  "updatedAt": "2022-12-01T15:54:23.000Z",
  "checkedAt": "2022-12-01T15:54:23.000Z",
  "id": 98520,
  "type": "anime",
  "title": "Zoku Touken Ranbu: Hanamaru",
  "altTitle": [
    "Touken Ranbu: Hanamaru 2",
    "続刀剣乱舞-花丸-"
  ],
  "url": "https://anilist.co/anime/98520",
  "image": "https://s4.anilist.co/file/anilistcdn/media/anime/cover/medium/bx98520-R33zIZW34dnm.jpg",
  "category": "tv",
  "hentai": false,
  "externalLinks": [
    {
      "site": "Crunchyroll",
      "url": "http://www.crunchyroll.com/touken-ranbu-hanamaru"
    },
    {
      "site": "Funimation",
      "url": "https://www.funimation.com/shows/touken-ranbu-hanamaru/"
    }
  ],
  "malId": 34863,
  "deletedAt": null,
  "Pages": {
    "9anime": {
      "4m3k": {
        "createdAt": "2020-10-12T15:50:06.000Z",
        "updatedAt": "2022-09-28T21:15:34.517Z",
        "checkedAt": null,
        "id": 2271,
        "identifier": "4m3k",
        "type": "anime",
        "page": "9anime",
        "title": "Zoku Touken Ranbu: Hanamaru",
        "url": "https://9anime.pl/watch/zoku-touken-ranbu-hanamaru.4m3k",
        "image": "https://images2-focus-opensocial.googleusercontent.com/gadgets/proxy?container=focus&amp;gadget=a&amp;no_expand=1&amp;refresh=604800&amp;url=http://2.bp.blogspot.com/-_p1CBBMo_Oc/WbpXYh_SsmI/AAAAAAAAAM0/88YSfgjFjrkBziRKq-j9dsVMa9D_8E9JwCHMYCw/s0/",
        "hentai": false,
        "sticky": false,
        "active": true,
        "actorId": null,
        "malId": 34863,
        "aniId": 98520,
        "deletedAt": null
      }
    },
    "Gogoanime": {
      "zoku-touken-ranbu-hanamaru": {
        "createdAt": "2020-10-12T16:02:23.000Z",
        "updatedAt": "2022-09-28T21:00:05.596Z",
        "checkedAt": null,
        "id": 21695,
        "identifier": "zoku-touken-ranbu-hanamaru",
        "type": "anime",
        "page": "Gogoanime",
        "title": "Zoku Touken Ranbu: Hanamaru",
        "url": "https://gogoanime.tel/category/zoku-touken-ranbu-hanamaru",
        "image": "https://images.gogoanime.tv/cover/zoku-touken-ranbu-hanamaru.png",
        "hentai": false,
        "sticky": false,
        "active": true,
        "actorId": null,
        "malId": 34863,
        "aniId": 98520,
        "deletedAt": null
      },
      "zoku-touken-ranbu-hanamaru-dub": {
        "createdAt": "2020-10-12T16:02:23.000Z",
        "updatedAt": "2022-09-28T21:00:05.596Z",
        "checkedAt": null,
        "id": 21696,
        "identifier": "zoku-touken-ranbu-hanamaru-dub",
        "type": "anime",
        "page": "Gogoanime",
        "title": "Zoku Touken Ranbu: Hanamaru (Dub)",
        "url": "https://gogoanime.tel/category/zoku-touken-ranbu-hanamaru-dub",
        "image": "https://cdnimg.xyz/cover/zoku-touken-ranbu-hanamaru-dub.png",
        "hentai": false,
        "sticky": false,
        "active": true,
        "actorId": null,
        "malId": 34863,
        "aniId": 98520,
        "deletedAt": null
      }
    }
  }
}