{
  "createdAt": "2021-05-20T14:43:25.000Z",
  "updatedAt": "2022-05-15T11:11:11.000Z",
  "checkedAt": "2022-05-15T11:11:11.000Z",
  "id": 98521,
  "type": "anime",
  "title": "Time Bokan: Gyakushuu no San-Akunin",
  "altTitle": [
    "Time Bokan: The Villains' Strike Back",
    "タイムボカン 逆襲の三悪人",
    "Time Bokan: Three Bad Guys' Counterattack",
    "Time Bokan 24 2nd Season"
  ],
  "url": "https://anilist.co/anime/98521",
  "image": "https://s4.anilist.co/file/anilistcdn/media/anime/cover/medium/bx98521-WTX6Uvf7DivL.png",
  "category": "tv",
  "hentai": false,
  "externalLinks": [
    {
      "site": "Crunchyroll",
      "url": "http://www.crunchyroll.com/time-bokan-24"
    }
  ],
  "malId": 35254,
  "deletedAt": null,
  "Pages": {
    "9anime": {
      "4mpk": {
        "createdAt": "2020-10-12T15:50:07.000Z",
        "updatedAt": "2021-05-20T15:21:50.000Z",
        "checkedAt": null,
        "id": 2281,
        "identifier": "4mpk",
        "type": "anime",
        "page": "9anime",
        "title": "Time Bokan: Gyakushuu no San Akunin",
        "url": "https://9anime.to/watch/time-bokan-gyakushuu-no-san-akunin.4mpk",
        "image": "https://images2-focus-opensocial.googleusercontent.com/gadgets/proxy?container=focus&amp;gadget=a&amp;no_expand=1&amp;refresh=604800&amp;url=http://2.bp.blogspot.com/-NFOo3L7Csjc/Wdi3TQnJqZI/AAAAAAAACLY/NdQ6_b8pMy8QXNrNKWKvvyUuelo1FOpegCHMYCw/s0/",
        "hentai": false,
        "sticky": false,
        "active": true,
        "actorId": null,
        "malId": 35254,
        "aniId": 98521,
        "deletedAt": null
      }
    },
    "Gogoanime": {
      "time-bokan-gyakushuu-no-san-akunin": {
        "createdAt": "2020-10-12T16:02:05.000Z",
        "updatedAt": "2021-05-20T15:21:55.000Z",
        "checkedAt": null,
        "id": 21107,
        "identifier": "time-bokan-gyakushuu-no-san-akunin",
        "type": "anime",
        "page": "Gogoanime",
        "title": "Time Bokan: Gyakushuu no San Akunin",
        "url": "https://gogoanime.vc/category/time-bokan-gyakushuu-no-san-akunin",
        "image": "https://images.gogoanime.tv/cover/time-bokan-gyakushuu-no-san-akunin.png",
        "hentai": false,
        "sticky": false,
        "active": true,
        "actorId": null,
        "malId": 35254,
        "aniId": 98521,
        "deletedAt": null
      }
    }
  }
}