{
  "createdAt": "2022-07-20T00:00:14.549Z",
  "updatedAt": "2022-07-20T00:00:15.000Z",
  "checkedAt": "2022-07-20T00:00:14.000Z",
  "id": 110738,
  "identifier": "numeros",
  "type": "manga",
  "page": "MangaFox",
  "title": "Numeros",
  "url": "https://fanfox.net/manga/numeros/",
  "image": "https://fmcdn.mfcdn.net/store/manga/25141/cover.jpg",
  "hentai": false,
  "sticky": false,
  "active": true,
  "actorId": null,
  "malId": null,
  "aniId": null,
  "deletedAt": null,
  "authors": [
    "Ronjay Valdenor"
  ],
  "Mal": null,
  "Ani": null
}