{
  "createdAt": "2021-06-18T12:55:58.000Z",
  "updatedAt": "2021-12-18T13:49:09.000Z",
  "checkedAt": null,
  "id": 78774,
  "identifier": "manga-gg983641",
  "type": "manga",
  "page": "MangaNato",
  "title": "I Don't Want To Become Crown Princess!!",
  "url": "https://readmanganato.com/manga-gg983641",
  "image": "https://avt.mkklcdnv6temp.com/46/f/19-1583500859.jpg",
  "hentai": false,
  "sticky": false,
  "active": true,
  "actorId": null,
  "malId": 122449,
  "aniId": 116405,
  "deletedAt": null,
  "authors": [
    "Saki Tsukigami",
    "Kuroki Natsu"
  ],
  "Mal": {
    "createdAt": "2020-12-14T12:19:05.000Z",
    "updatedAt": "2022-01-30T06:50:40.000Z",
    "checkedAt": null,
    "id": 122449,
    "type": "manga",
    "title": "Outaishihi ni nante Naritakunai!!",
    "altTitle": [
      "I Don't Want to Become Crown Princess!!",
      "I Don't Want to Be the Crown Princess.",
      "I’ll Never Be Your Crown Princess!",
      "王太子妃になんてなりたくない!!"
    ],
    "url": "https://myanimelist.net/manga/122449/Outaishihi_ni_nante_Naritakunai",
    "image": "https://cdn.myanimelist.net/images/manga/2/233443.jpg",
    "category": "Manga",
    "hentai": false,
    "externalLinks": [
      {
        "site": "officialsite",
        "url": "https://online.ichijinsha.co.jp/zerosum/comic/otaishihi"
      }
    ],
    "legalLinks": [],
    "deletedAt": null,
    "authors": [
      "Tsukigami, Saki",
      "Kuroki, Natsu"
    ]
  },
  "Ani": {
    "createdAt": "2022-05-13T12:59:55.597Z",
    "updatedAt": "2022-05-13T12:59:55.597Z",
    "checkedAt": null,
    "id": 116405,
    "type": "manga",
    "title": "Outaishihi ni Nante Naritakunai!!",
    "altTitle": [
      "I’ll Never Be Your Crown Princess!",
      "王太子妃になんてなりたくない!!",
      "¡No quiero ser la Princesa Heredera!",
      "I Don't Want to Become Crown Princess!!  "
    ],
    "url": "https://anilist.co/manga/116405",
    "image": "https://s4.anilist.co/file/anilistcdn/media/manga/cover/medium/bx116405-AiLgHyWsYe76.jpg",
    "category": "manga",
    "hentai": false,
    "externalLinks": [],
    "malId": 122449,
    "deletedAt": null,
    "authors": [
      "Saki Tsukigami",
      "Natsu Kuroki",
      "En Tsutamori"
    ]
  }
}