{
  "createdAt": "2022-07-06T09:30:05.390Z",
  "updatedAt": "2022-07-06T09:30:05.000Z",
  "checkedAt": "2022-07-06T09:30:05.000Z",
  "id": 109000,
  "identifier": "manga-oo991523",
  "type": "manga",
  "page": "MangaNato",
  "title": "There's No Friendship Between The Grand Duke And The Marquis",
  "url": "https://readmanganato.com/manga-oo991523",
  "image": "https://avt.mkklcdnv6temp.com/20/k/26-1657098969.jpg",
  "hentai": false,
  "sticky": false,
  "active": true,
  "actorId": null,
  "malId": null,
  "aniId": null,
  "deletedAt": null,
  "authors": [
    "Tiba",
    "Yell Yell"
  ],
  "Mal": null,
  "Ani": null
}