{
  "createdAt": "2022-03-29T03:23:40.000Z",
  "updatedAt": "2022-03-29T03:53:38.000Z",
  "checkedAt": null,
  "id": 100195,
  "identifier": "manga-ei954365",
  "type": "manga",
  "page": "MangaNato",
  "title": "Onedari Girl",
  "url": "https://manganato.com/manga-ei954365",
  "image": "https://avt.mkklcdnv6temp.com/5/l/3-1583467847.jpg",
  "hentai": false,
  "sticky": false,
  "active": true,
  "actorId": null,
  "malId": 59863,
  "aniId": 86329,
  "deletedAt": null,
  "authors": [
    "Fukami Sakana"
  ],
  "Mal": {
    "createdAt": "2020-10-12T15:44:55.000Z",
    "updatedAt": "2023-01-19T03:39:36.000Z",
    "checkedAt": "2023-01-19T03:39:36.000Z",
    "id": 59863,
    "type": "manga",
    "title": "Onedari Girl",
    "altTitle": [
      "Pestering Girl",
      "おねだりガール"
    ],
    "url": "https://myanimelist.net/manga/59863/Onedari_Girl",
    "image": "https://cdn.myanimelist.net/images/manga/3/106313.jpg",
    "category": "Manga",
    "hentai": false,
    "externalLinks": [],
    "legalLinks": [],
    "deletedAt": null,
    "authors": [
      "Fukami, Sakana"
    ]
  },
  "Ani": {
    "createdAt": "2022-05-13T12:46:18.877Z",
    "updatedAt": "2023-01-19T03:39:36.000Z",
    "checkedAt": "2023-01-19T03:39:36.000Z",
    "id": 86329,
    "type": "manga",
    "title": "Onedari Girl",
    "altTitle": [
      "おねだりガール",
      "Pestering Girl"
    ],
    "url": "https://anilist.co/manga/86329",
    "image": "https://s4.anilist.co/file/anilistcdn/media/manga/cover/medium/56329-cGW3Wq5UAh3S.jpg",
    "category": "manga",
    "hentai": false,
    "externalLinks": [],
    "malId": 59863,
    "deletedAt": null,
    "authors": [
      "Sakana Fukami"
    ]
  }
}