{
  "createdAt": "2021-06-09T18:34:26.000Z",
  "updatedAt": "2021-12-09T19:34:09.000Z",
  "checkedAt": null,
  "id": 77488,
  "identifier": "manga-bi979065",
  "type": "manga",
  "page": "MangaNato",
  "title": "I Decided To Fake A Marriage With My Junior (♀️) To Shut My Parents Up",
  "url": "https://readmanganato.com/manga-bi979065",
  "image": "https://avt.mkklcdnv6temp.com/27/m/16-1583494457.jpg",
  "hentai": false,
  "sticky": false,
  "active": true,
  "actorId": null,
  "malId": 114120,
  "aniId": 102047,
  "deletedAt": null,
  "authors": [
    "Kodama Naoko"
  ],
  "Mal": {
    "createdAt": "2020-10-12T15:47:34.000Z",
    "updatedAt": "2022-05-15T01:35:30.000Z",
    "checkedAt": "2022-05-15T01:35:30.000Z",
    "id": 114120,
    "type": "manga",
    "title": "Oya ga Urusai node Kouhai (♀) to Gisou Kekkon Shitemita.",
    "altTitle": [
      "I Decided to Fake a Marriage With My Junior to Shut My Parents Up.",
      "I Camouflage Marriage with a Junior (♀️) Because My Parent is Very Noisy",
      "Musanso Renai",
      "Anaerobic Love",
      "I Married My Best Friend to Shut My Parents Up",
      "親がうるさいので後輩(♀)と偽装結婚してみた。"
    ],
    "url": "https://myanimelist.net/manga/114120/Oya_ga_Urusai_node_Kouhai_♀_to_Gisou_Kekkon_Shitemita",
    "image": "https://cdn.myanimelist.net/images/manga/1/212825.jpg",
    "category": "Manga",
    "hentai": false,
    "externalLinks": [
      {
        "site": "wikipedia",
        "url": "https://ja.wikipedia.org/wiki/%E8%A6%AA%E3%81%8C%E3%81%86%E3%82%8B%E3%81%95%E3%81%84%E3%81%AE%E3%81%A7%E5%BE%8C%E8%BC%A9(%E2%99%80)%E3%81%A8%E5%81%BD%E8%A3%85%E7%B5%90%E5%A9%9A%E3%81%97%E3%81%A6%E3%81%BF%E3%81%9F%E3%80%82"
      }
    ],
    "legalLinks": [],
    "deletedAt": null,
    "authors": [
      "Kodama, Naoko"
    ]
  },
  "Ani": {
    "createdAt": "2022-05-13T12:57:56.918Z",
    "updatedAt": "2022-05-16T01:15:56.000Z",
    "checkedAt": "2022-05-16T01:15:56.000Z",
    "id": 102047,
    "type": "manga",
    "title": "Oya ga Urusai node Kouhai (♀) to Gisou Kekkon shitemita.",
    "altTitle": [
      "I Married My Best Friend to Shut My Parents Up",
      "親がうるさいので後輩（♀）と偽装結婚してみた。",
      "I decided to fake a marriage with my junior (♀️) to shut my parents up",
      "I Decided to Fake a Marriage with My Junior to Shut My Parents Up",
      "รำคาญนักก็แต่งงานกันซะเลย"
    ],
    "url": "https://anilist.co/manga/102047",
    "image": "https://s4.anilist.co/file/anilistcdn/media/manga/cover/medium/bx102047-wdH5eEKLyEM9.png",
    "category": "manga",
    "hentai": false,
    "externalLinks": [],
    "malId": 114120,
    "deletedAt": null,
    "authors": [
      "Naoko Kodama",
      "Amber Tamosaitis"
    ]
  }
}