{
  "createdAt": "2020-10-12T15:56:05.000Z",
  "updatedAt": "2022-09-28T21:15:34.517Z",
  "checkedAt": null,
  "id": 9613,
  "identifier": "w276",
  "type": "anime",
  "page": "9anime",
  "title": "In Search of Axis",
  "url": "https://9anime.pl/watch/in-search-of-axis.w276",
  "image": "https://static.akacdn.ru/files/images/2019/02/8bf4a0cf71f7f8580e40810f62545ebe.jpg",
  "hentai": false,
  "sticky": false,
  "active": true,
  "actorId": null,
  "malId": 34720,
  "aniId": 102567,
  "deletedAt": null,
  "Mal": {
    "createdAt": "2020-10-12T15:39:51.000Z",
    "updatedAt": "2022-12-11T20:27:08.000Z",
    "checkedAt": "2022-12-11T20:27:08.000Z",
    "id": 34720,
    "type": "anime",
    "title": "In Search of Axis",
    "altTitle": [
      "In Search of New Axis",
      "In Search of Muscular Axis",
      "In Search of Performing Axis",
      "In Search of Axis",
      "In Search of Axis"
    ],
    "url": "https://myanimelist.net/anime/34720/In_Search_of_Axis",
    "image": "https://cdn.myanimelist.net/images/anime/1409/95844.jpg",
    "category": "Special",
    "hentai": false,
    "externalLinks": [
      {
        "site": "officialsite",
        "url": "http://www.ppi.co.jp/works/in-search-of-axis-series/"
      },
      {
        "site": "wikipedia",
        "url": "https://en.wikipedia.org/wiki/Polygon_Pictures"
      }
    ],
    "legalLinks": [],
    "deletedAt": null,
    "anidbId": null
  },
  "Ani": {
    "createdAt": "2021-05-20T14:43:22.000Z",
    "updatedAt": "2022-12-11T20:27:07.000Z",
    "checkedAt": "2022-12-11T20:27:07.000Z",
    "id": 102567,
    "type": "anime",
    "title": "In Search of Axis",
    "altTitle": [
      "In Search of Axis",
      "In Search of New Axis",
      "In Search of Muscular Axis",
      "In Search of Muscular Axis"
    ],
    "url": "https://anilist.co/anime/102567",
    "image": "https://s4.anilist.co/file/anilistcdn/media/anime/cover/medium/102567-L90uPlsiYLOE.jpg",
    "category": "special",
    "hentai": false,
    "externalLinks": [],
    "malId": 34720,
    "deletedAt": null
  }
}