{
  "createdAt": "2022-05-13T12:51:44.728Z",
  "updatedAt": "2022-06-12T00:43:21.000Z",
  "checkedAt": "2022-06-12T00:43:21.000Z",
  "id": 101212,
  "type": "manga",
  "title": "Xian se Qingyin",
  "altTitle": [
    "Timbre in His Heart",
    "弦色清音"
  ],
  "url": "https://anilist.co/manga/101212",
  "image": "https://s4.anilist.co/file/anilistcdn/media/manga/cover/medium/101212-ZNYplennuMKY.jpg",
  "category": "manga",
  "hentai": false,
  "externalLinks": [],
  "malId": null,
  "deletedAt": null,
  "authors": [
    "Baixiong Dao Er"
  ],
  "Pages": {}
}