{
  "createdAt": "2022-05-13T13:02:07.302Z",
  "updatedAt": "2022-05-13T13:02:07.302Z",
  "checkedAt": null,
  "id": 104909,
  "type": "manga",
  "title": "Seitokaichou ni Chuukoku Koushiki Anthology",
  "altTitle": [
    "生徒会長に忠告 公式アンソロジー",
    "Seitokaichou ni Chukoku Official Anthology"
  ],
  "url": "https://anilist.co/manga/104909",
  "image": "https://s4.anilist.co/file/anilistcdn/media/manga/cover/medium/nx104909-dNy0v7X6Hh8C.jpg",
  "category": "manga",
  "hentai": false,
  "externalLinks": [],
  "malId": null,
  "deletedAt": null,
  "authors": [
    "Tamaki Oujima",
    "Ayako Catherine",
    "CJ Michalski",
    "Akane Abe",
    "Gido Amagakure"
  ],
  "Pages": {}
}