{
  "createdAt": "2022-05-13T12:56:46.473Z",
  "updatedAt": "2022-05-13T12:56:46.473Z",
  "checkedAt": null,
  "id": 111250,
  "type": "manga",
  "title": "Kaichou no Megane Densetsu",
  "altTitle": [
    "会長の眼鏡伝説",
    "The Legend of the President's Glasses"
  ],
  "url": "https://anilist.co/manga/111250",
  "image": "https://s4.anilist.co/file/anilistcdn/media/manga/cover/medium/bx111250-X6a1dXUA7rpf.png",
  "category": "one_shot",
  "hentai": false,
  "externalLinks": [],
  "malId": null,
  "deletedAt": null,
  "authors": [
    "Aki Irie"
  ],
  "Pages": {
    "Mangadex": {
      "ccb5c3ee-c4d3-4a86-9cf8-eeadfff1ab08": {
        "createdAt": "2020-10-12T16:11:08.000Z",
        "updatedAt": "2021-12-05T09:23:01.000Z",
        "checkedAt": null,
        "id": 18658,
        "identifier": "ccb5c3ee-c4d3-4a86-9cf8-eeadfff1ab08",
        "type": "manga",
        "page": "Mangadex",
        "title": "The Legend of the President's Glasses",
        "url": "https://mangadex.org/title/ccb5c3ee-c4d3-4a86-9cf8-eeadfff1ab08",
        "image": "https://uploads.mangadex.org/covers/ccb5c3ee-c4d3-4a86-9cf8-eeadfff1ab08/9ba09b26-3373-43cd-944d-aede7b1dccbd.png",
        "hentai": false,
        "sticky": false,
        "active": true,
        "actorId": null,
        "malId": null,
        "aniId": 111250,
        "deletedAt": null,
        "authors": [
          "Irie Aki"
        ]
      }
    }
  }
}