{
  "createdAt": "2022-05-13T12:59:06.022Z",
  "updatedAt": "2022-05-13T12:59:06.022Z",
  "checkedAt": null,
  "id": 112556,
  "type": "manga",
  "title": "Isekai Sniper wa Onna Senshi no Mofumofu Pet",
  "altTitle": [
    "異世界狙撃手は女戦士のモフモフ愛玩動物",
    "The Fantasy World Sniper is the Fluffy Pet of the Woman Warrior"
  ],
  "url": "https://anilist.co/manga/112556",
  "image": "https://s4.anilist.co/file/anilistcdn/media/manga/cover/medium/bx112556-nipfQ7DCfAv4.png",
  "category": "manga",
  "hentai": true,
  "externalLinks": [],
  "malId": 127075,
  "deletedAt": null,
  "authors": [
    "Inomaru",
    "Yasunori Mitsunaga"
  ],
  "Pages": {}
}