{
  "createdAt": "2022-05-13T13:00:45.204Z",
  "updatedAt": "2022-05-13T13:00:45.204Z",
  "checkedAt": null,
  "id": 112574,
  "type": "manga",
  "title": "Kimi ga Tonari ni Iru Dake de: Aisubeki Doubutsu-tachi",
  "altTitle": [
    "君がとなりにいるだけで　～愛すべき動物たち～",
    "As Long As You're By My Side",
    "Kimi ga Tonari ni Iru Dake de: Ai Subeki Doubutsu-tachi"
  ],
  "url": "https://anilist.co/manga/112574",
  "image": "https://s4.anilist.co/file/anilistcdn/media/manga/cover/medium/b112574-7IlZpAKf1lVO.jpg",
  "category": "manga",
  "hentai": false,
  "externalLinks": [],
  "malId": null,
  "deletedAt": null,
  "authors": [
    "est em",
    "Youko Nemu",
    "Chie Shinohara",
    "Keiko Nishi",
    "Hozumi",
    "Mieko Osaka",
    "Akiko Hatsu",
    "Eiko Oouchi",
    "Asuka  Sakurawa"
  ],
  "Pages": {}
}