{
  "createdAt": "2022-05-13T13:06:34.651Z",
  "updatedAt": "2022-05-13T13:06:34.651Z",
  "checkedAt": null,
  "id": 117247,
  "type": "manga",
  "title": "See You Later, Mermaid",
  "altTitle": [
    "See you later, Mermaid",
    "シーユーレイター、マーメイド"
  ],
  "url": "https://anilist.co/manga/117247",
  "image": "https://s4.anilist.co/file/anilistcdn/media/manga/cover/medium/bx117247-kX1ZXswluMha.jpg",
  "category": "manga",
  "hentai": false,
  "externalLinks": [],
  "malId": 125422,
  "deletedAt": null,
  "authors": [
    "Dentou Hayane"
  ],
  "Pages": {}
}