{
  "createdAt": "2022-05-13T12:54:24.108Z",
  "updatedAt": "2022-12-13T15:35:50.000Z",
  "checkedAt": "2022-12-13T15:35:50.000Z",
  "id": 120440,
  "type": "manga",
  "title": "Agiga Saenggyeosseoyo",
  "altTitle": [
    "Positively Yours",
    "아기가 생겼어요",
    "我有孩子了",
    "子供ができました",
    "理事長和我的祕密關係"
  ],
  "url": "https://anilist.co/manga/120440",
  "image": "https://s4.anilist.co/file/anilistcdn/media/manga/cover/medium/bx120440-PdrYcdsMheyO.jpg",
  "category": "manga",
  "hentai": false,
  "externalLinks": [],
  "malId": 140921,
  "deletedAt": null,
  "authors": [
    "Gi Kang",
    "Lee Jung"
  ],
  "Pages": {
    "Mangadex": {
      "40da1219-1860-4d7f-b823-d3511ac67cac": {
        "createdAt": "2020-10-12T16:20:17.000Z",
        "updatedAt": "2022-11-04T13:55:44.000Z",
        "checkedAt": "2022-11-03T23:30:02.000Z",
        "id": 36895,
        "identifier": "40da1219-1860-4d7f-b823-d3511ac67cac",
        "type": "manga",
        "page": "Mangadex",
        "title": "Positively Yours",
        "url": "https://mangadex.org/title/40da1219-1860-4d7f-b823-d3511ac67cac",
        "image": "https://uploads.mangadex.org/covers/40da1219-1860-4d7f-b823-d3511ac67cac/2e5569b8-76c4-401f-a59d-e2aa37ff6d1c.jpg",
        "hentai": false,
        "sticky": false,
        "active": true,
        "actorId": 1,
        "malId": 140921,
        "aniId": 120440,
        "deletedAt": null,
        "authors": [
          "Lee Jung",
          "Kang Ki"
        ]
      }
    },
    "MangaSee": {
      "positively-yours": {
        "createdAt": "2021-04-27T15:21:13.000Z",
        "updatedAt": "2023-01-15T22:00:14.000Z",
        "checkedAt": "2023-01-15T22:00:14.000Z",
        "id": 70348,
        "identifier": "positively-yours",
        "type": "manga",
        "page": "MangaSee",
        "title": "Positively Yours",
        "url": "https://mangasee123.com/manga/Positively-Yours",
        "image": "https://temp.compsci88.com/cover/Positively-Yours.jpg",
        "hentai": false,
        "sticky": false,
        "active": true,
        "actorId": 1,
        "malId": 140921,
        "aniId": 120440,
        "deletedAt": null,
        "authors": [
          "KANG Ki",
          "LEE Jung"
        ]
      }
    },
    "MangaFox": {
      "positively_yours": {
        "createdAt": "2021-08-26T02:07:13.000Z",
        "updatedAt": "2022-02-26T02:17:39.000Z",
        "checkedAt": null,
        "id": 86228,
        "identifier": "positively_yours",
        "type": "manga",
        "page": "MangaFox",
        "title": "Positively Yours",
        "url": "https://fanfox.net/manga/positively_yours/",
        "image": "https://fmcdn.mfcdn.net/store/manga/38282/cover.jpg",
        "hentai": false,
        "sticky": false,
        "active": true,
        "actorId": null,
        "malId": null,
        "aniId": 120440,
        "deletedAt": null,
        "authors": [
          "KANG Ki",
          "LEE Jung"
        ]
      }
    }
  }
}