{
  "createdAt": "2022-05-13T12:41:00.062Z",
  "updatedAt": "2022-05-13T12:41:00.062Z",
  "checkedAt": null,
  "id": 123141,
  "type": "manga",
  "title": "Xindong Yujing",
  "altTitle": [
    "Caution! Love Around the Corner",
    "心动预警",
    "Love & Order",
    "Heartbeat Alert"
  ],
  "url": "https://anilist.co/manga/123141",
  "image": "https://s4.anilist.co/file/anilistcdn/media/manga/cover/medium/bx123141-n3cNc98WqIJQ.jpg",
  "category": "manga",
  "hentai": false,
  "externalLinks": [],
  "malId": null,
  "deletedAt": null,
  "authors": [
    "FanFan Dongman",
    "Gun Zi",
    "Kong Zao"
  ],
  "Pages": {}
}