{
  "createdAt": "2022-05-13T12:42:24.118Z",
  "updatedAt": "2022-12-04T19:21:37.000Z",
  "checkedAt": "2022-12-04T19:21:37.000Z",
  "id": 123920,
  "type": "manga",
  "title": "Tonari no Nobukuni-san wa Ore no Koto ga Suki na Ki ga Suru",
  "altTitle": [
    "I Get the Feeling That Nobukuni-san Likes Me",
    "となりの信國さんは俺のことが好きな気がする",
    "\"NOBUKUNI-SAN\" Does She Like Me?"
  ],
  "url": "https://anilist.co/manga/123920",
  "image": "https://s4.anilist.co/file/anilistcdn/media/manga/cover/medium/bx123920-NlhsEM7y4TOu.jpg",
  "category": "manga",
  "hentai": false,
  "externalLinks": [],
  "malId": 131119,
  "deletedAt": null,
  "authors": [
    "Kousuke Yasuda",
    "Miki Z",
    "Robert Harkins"
  ],
  "Pages": {
    "Mangadex": {
      "7b3eacca-6f5a-48ce-8c8f-0ecaa78368b5": {
        "createdAt": "2020-12-23T06:26:04.000Z",
        "updatedAt": "2023-01-21T07:30:17.000Z",
        "checkedAt": "2023-01-21T07:30:17.000Z",
        "id": 55418,
        "identifier": "7b3eacca-6f5a-48ce-8c8f-0ecaa78368b5",
        "type": "manga",
        "page": "Mangadex",
        "title": "Tonari no Nobukuni-san wa Ore no Koto ga Sukina Ki ga Suru",
        "url": "https://mangadex.org/title/7b3eacca-6f5a-48ce-8c8f-0ecaa78368b5",
        "image": "https://uploads.mangadex.org/covers/7b3eacca-6f5a-48ce-8c8f-0ecaa78368b5/d1c8d787-6242-4330-8bc6-8131b7af70a6.jpg",
        "hentai": false,
        "sticky": false,
        "active": true,
        "actorId": null,
        "malId": 131119,
        "aniId": 123920,
        "deletedAt": null,
        "authors": [
          "Yasuda Kousuke"
        ]
      }
    },
    "MangaNato": {
      "manga-la988557": {
        "createdAt": "2021-07-23T10:53:50.000Z",
        "updatedAt": "2022-01-23T11:30:11.000Z",
        "checkedAt": null,
        "id": 82810,
        "identifier": "manga-la988557",
        "type": "manga",
        "page": "MangaNato",
        "title": "\"nobukuni-San\" Does She Like Me?",
        "url": "https://manganato.com/manga-la988557",
        "image": "https://avt.mkklcdnv6temp.com/43/s/23-1616141627.jpg",
        "hentai": false,
        "sticky": false,
        "active": true,
        "actorId": null,
        "malId": 131119,
        "aniId": 123920,
        "deletedAt": null,
        "authors": [
          "Yasuda Kousuke"
        ]
      }
    },
    "MangaFox": {
      "tonari_no_nobukuni_san_wa_ore_no_koto_ga_suki_na_ki_ga_suru": {
        "createdAt": "2021-07-31T14:22:53.000Z",
        "updatedAt": "2022-01-31T15:20:42.000Z",
        "checkedAt": null,
        "id": 83425,
        "identifier": "tonari_no_nobukuni_san_wa_ore_no_koto_ga_suki_na_ki_ga_suru",
        "type": "manga",
        "page": "MangaFox",
        "title": "Tonari no Nobukuni-san wa Ore no Koto ga Suki na Ki ga Suru",
        "url": "https://fanfox.net/manga/tonari_no_nobukuni_san_wa_ore_no_koto_ga_suki_na_ki_ga_suru/",
        "image": "https://fmcdn.mfcdn.net/store/manga/38040/cover.jpg",
        "hentai": false,
        "sticky": false,
        "active": true,
        "actorId": null,
        "malId": 131119,
        "aniId": 123920,
        "deletedAt": null,
        "authors": [
          "YASUDA Kousuke"
        ]
      }
    },
    "MangaSee": {
      "i-get-the-feeling-that-nobukuni-san-likes-me": {
        "createdAt": "2022-12-27T01:00:16.151Z",
        "updatedAt": "2022-12-27T01:20:00.000Z",
        "checkedAt": "2022-12-27T01:00:16.000Z",
        "id": 120510,
        "identifier": "i-get-the-feeling-that-nobukuni-san-likes-me",
        "type": "manga",
        "page": "MangaSee",
        "title": "I Get the Feeling That Nobukuni-san Likes Me",
        "url": "https://mangasee123.com/manga/I-Get-the-Feeling-That-Nobukuni-san-Likes-Me",
        "image": "https://temp.compsci88.com/cover/I-Get-the-Feeling-That-Nobukuni-san-Likes-Me.jpg",
        "hentai": false,
        "sticky": false,
        "active": true,
        "actorId": null,
        "malId": 131119,
        "aniId": 123920,
        "deletedAt": null,
        "authors": [
          "YASUDA Kousuke"
        ]
      }
    }
  }
}