{
  "createdAt": "2022-05-13T12:53:55.990Z",
  "updatedAt": "2022-08-09T02:20:38.000Z",
  "checkedAt": "2022-08-09T02:20:38.000Z",
  "id": 125299,
  "type": "manga",
  "title": "Kyuukyoku Choujin EVOLUTION",
  "altTitle": [
    "究極超人あ～る EVOLUTION"
  ],
  "url": "https://anilist.co/manga/125299",
  "image": "https://s4.anilist.co/file/anilistcdn/media/manga/cover/medium/bx125299-Q80ymWOkHSs6.jpg",
  "category": "one_shot",
  "hentai": false,
  "externalLinks": [],
  "malId": null,
  "deletedAt": null,
  "authors": [
    "Masami Yuuki"
  ],
  "Pages": {}
}