{
  "createdAt": "2022-05-13T12:53:36.858Z",
  "updatedAt": "2022-09-03T19:34:26.000Z",
  "checkedAt": "2022-09-03T19:34:26.000Z",
  "id": 145264,
  "type": "manga",
  "title": "Chao Shen Zhi Ka Shi",
  "altTitle": [
    "超神制卡师"
  ],
  "url": "https://anilist.co/manga/145264",
  "image": "https://s4.anilist.co/file/anilistcdn/media/manga/cover/medium/bx145264-TvoEwnzV0tVL.jpg",
  "category": "manga",
  "hentai": false,
  "externalLinks": [],
  "malId": null,
  "deletedAt": null,
  "authors": [
    "Lingxia Jiushi Du",
    "Chi Bu Pang",
    "Fan Hua"
  ],
  "Pages": {
    "MangaNato": {
      "manga-mz989682": {
        "createdAt": "2021-09-21T05:10:54.000Z",
        "updatedAt": "2022-02-17T22:44:02.000Z",
        "checkedAt": null,
        "id": 87400,
        "identifier": "manga-mz989682",
        "type": "manga",
        "page": "MangaNato",
        "title": "Super God Card Maker",
        "url": "https://readmanganato.com/manga-mz989682",
        "image": "https://avt.mkklcdnv6temp.com/42/h/24-1632197031.jpg",
        "hentai": false,
        "sticky": false,
        "active": true,
        "actorId": 1,
        "malId": null,
        "aniId": 145264,
        "deletedAt": null,
        "authors": [
          "Updating"
        ]
      }
    }
  }
}