{
  "altTitle": [
    "Migratory Fish"
  ],
  "externalLinks": [],
  "authors": [
    "Ouji Kuzunoha"
  ],
  "id": 149474,
  "malId": null,
  "type": "manga",
  "title": "Migratory Fish",
  "url": "https://anilist.co/manga/149474",
  "image": "https://s4.anilist.co/file/anilistcdn/media/manga/cover/medium/bx149474-ms80Cc6Uf3pI.jpg",
  "category": "one_shot",
  "hentai": false,
  "createdAt": "2022-05-18T13:00:20.000Z",
  "updatedAt": "2022-05-18T13:00:20.000Z",
  "deletedAt": null,
  "Pages": {}
}