{
  "createdAt": "2022-05-13T12:50:15.108Z",
  "updatedAt": "2022-05-13T12:50:15.108Z",
  "checkedAt": null,
  "id": 31314,
  "type": "manga",
  "title": "100 Ways of an Exorcist",
  "altTitle": [
    "100 Ways of an Exorcist",
    "幽子ちゃん100連発!!",
    "Yuuko-chan 100 Renpatsu!!"
  ],
  "url": "https://anilist.co/manga/31314",
  "image": "https://s4.anilist.co/file/anilistcdn/media/manga/cover/medium/1314.jpg",
  "category": "manga",
  "hentai": false,
  "externalLinks": [],
  "malId": 1314,
  "deletedAt": null,
  "authors": [
    "Kei Kusunoki"
  ],
  "Pages": {}
}