{
  "createdAt": "2022-05-13T13:02:49.873Z",
  "updatedAt": "2022-05-13T13:02:49.873Z",
  "checkedAt": null,
  "id": 34773,
  "type": "manga",
  "title": "Lovey Dovey",
  "altTitle": [
    "LOVEY DOVEY",
    "优女与恶男"
  ],
  "url": "https://anilist.co/manga/34773",
  "image": "https://s4.anilist.co/file/anilistcdn/media/manga/cover/medium/bx34773-cvs6YUTPPCA5.png",
  "category": "manga",
  "hentai": false,
  "externalLinks": [],
  "malId": 4773,
  "deletedAt": null,
  "authors": [
    "Aya Oda"
  ],
  "Pages": {}
}