{
  "createdAt": "2022-05-13T12:43:51.479Z",
  "updatedAt": "2022-05-13T12:43:51.479Z",
  "checkedAt": null,
  "id": 35615,
  "type": "manga",
  "title": "Sukisa Sukisa Sukisa",
  "altTitle": [
    "すきさ 好きさ すきさ",
    "Sukisa Zukisa Sukisa"
  ],
  "url": "https://anilist.co/manga/35615",
  "image": "https://s4.anilist.co/file/anilistcdn/media/manga/cover/medium/bx35615-36DTZi4y6XPp.png",
  "category": "manga",
  "hentai": false,
  "externalLinks": [],
  "malId": 5615,
  "deletedAt": null,
  "authors": [
    "Miwa Sakai"
  ],
  "Pages": {}
}