{
  "createdAt": "2022-05-13T13:00:50.265Z",
  "updatedAt": "2022-05-25T16:16:56.000Z",
  "checkedAt": "2022-05-25T16:16:56.000Z",
  "id": 38847,
  "type": "manga",
  "title": "Nogizaka Haruka no Himitsu",
  "altTitle": [
    "乃木坂春香の秘密",
    "Nogizaka Haruka's Secret",
    "Haruka Nogizaka's Secret"
  ],
  "url": "https://anilist.co/manga/38847",
  "image": "https://s4.anilist.co/file/anilistcdn/media/manga/cover/medium/bx38847-mbD3GfyJQ5dW.jpg",
  "category": "manga",
  "hentai": false,
  "externalLinks": [],
  "malId": 8847,
  "deletedAt": null,
  "authors": [
    "Yasuhiro Miyama",
    "Yuusaku Igarashi",
    "Shaa"
  ],
  "Pages": {}
}