{
  "createdAt": "2022-05-13T12:49:04.510Z",
  "updatedAt": "2022-05-13T12:49:04.510Z",
  "checkedAt": null,
  "id": 41802,
  "type": "manga",
  "title": "Kitsune to Atori",
  "altTitle": [
    "狐とアトリ―武田日向短編集",
    "The Dolls House",
    "The Doll's Girl",
    "Yaeka no Karute extra story"
  ],
  "url": "https://anilist.co/manga/41802",
  "image": "https://s4.anilist.co/file/anilistcdn/media/manga/cover/medium/11802.jpg",
  "category": "manga",
  "hentai": false,
  "externalLinks": [],
  "malId": 11802,
  "deletedAt": null,
  "authors": [
    "Hinata Takeda"
  ],
  "Pages": {}
}