{
  "createdAt": "2022-05-13T12:48:33.671Z",
  "updatedAt": "2022-05-13T12:48:33.671Z",
  "checkedAt": null,
  "id": 68167,
  "type": "manga",
  "title": "18 Rin",
  "altTitle": [
    "18倫",
    "Juuhachi Rin",
    "Rinko 18",
    "Rinko Eighteen"
  ],
  "url": "https://anilist.co/manga/68167",
  "image": "https://s4.anilist.co/file/anilistcdn/media/manga/cover/medium/bx68167-IWN4gwBwyAyV.jpg",
  "category": "manga",
  "hentai": false,
  "externalLinks": [],
  "malId": 38167,
  "deletedAt": null,
  "authors": [
    "Taka Matsumoto"
  ],
  "Pages": {
    "Mangadex": {
      "d6f7ac60-9478-461a-9369-e723d1c0c3c3": {
        "createdAt": "2020-10-12T16:13:01.000Z",
        "updatedAt": "2021-12-05T18:21:29.000Z",
        "checkedAt": null,
        "id": 22036,
        "identifier": "d6f7ac60-9478-461a-9369-e723d1c0c3c3",
        "type": "manga",
        "page": "Mangadex",
        "title": "18 Rin",
        "url": "https://mangadex.org/title/d6f7ac60-9478-461a-9369-e723d1c0c3c3",
        "image": "https://uploads.mangadex.org/covers/d6f7ac60-9478-461a-9369-e723d1c0c3c3/f405ab3d-fe37-456d-9a93-95aedd5df6dd.png",
        "hentai": false,
        "sticky": false,
        "active": true,
        "actorId": null,
        "malId": 38167,
        "aniId": 68167,
        "deletedAt": null,
        "authors": [
          "Matsumoto Taka"
        ]
      },
      "cdd4c44e-976a-43fd-9418-98a7b254bad8": {
        "createdAt": "2020-10-12T16:14:00.000Z",
        "updatedAt": "2021-12-06T01:48:41.000Z",
        "checkedAt": null,
        "id": 24032,
        "identifier": "cdd4c44e-976a-43fd-9418-98a7b254bad8",
        "type": "manga",
        "page": "Mangadex",
        "title": "Back to the Highteen",
        "url": "https://mangadex.org/title/cdd4c44e-976a-43fd-9418-98a7b254bad8",
        "image": "https://uploads.mangadex.org/covers/cdd4c44e-976a-43fd-9418-98a7b254bad8/eaf198aa-c9de-48f8-9d99-770f30c382ec.jpg",
        "hentai": false,
        "sticky": false,
        "active": true,
        "actorId": null,
        "malId": 38167,
        "aniId": 68167,
        "deletedAt": null,
        "authors": [
          "Kisun",
          "Hongseul"
        ]
      }
    }
  }
}