{
  "createdAt": "2022-05-13T13:06:06.448Z",
  "updatedAt": "2022-05-13T13:06:06.448Z",
  "checkedAt": null,
  "id": 85754,
  "type": "manga",
  "title": "Fate/Prototype: Sougin no Fragments",
  "altTitle": [
    "Fate/Prototype 蒼銀のフラグメンツ",
    "Fate/Prototype: Aoi Gin no Fragments",
    "Fate/Prototype: Fragments of Sky Silver",
    "Fate/Prototype: Pale Silver Fragments",
    "Fate/Prototype เศษเสี้ยวสีเงินคราม"
  ],
  "url": "https://anilist.co/manga/85754",
  "image": "https://s4.anilist.co/file/anilistcdn/media/manga/cover/medium/bx85754-9Zfg1wVSHjx0.jpg",
  "category": "novel",
  "hentai": false,
  "externalLinks": [],
  "malId": 61005,
  "deletedAt": null,
  "authors": [
    "Nakahara",
    "Hikaru Sakurai",
    "Kinoko Nasu",
    "Takashi Takeuchi",
    "Type-Moon"
  ],
  "Pages": {}
}