{
  "createdAt": "2022-05-13T12:54:26.609Z",
  "updatedAt": "2022-07-23T03:00:12.000Z",
  "checkedAt": "2022-07-23T03:00:12.000Z",
  "id": 85881,
  "type": "manga",
  "title": "Terror Infinity",
  "altTitle": [
    "无限恐怖",
    "Wu Xian Kong Bu"
  ],
  "url": "https://anilist.co/manga/85881",
  "image": "https://s4.anilist.co/file/anilistcdn/media/manga/cover/medium/55881-op95vuCf8pVj.jpg",
  "category": "manga",
  "hentai": false,
  "externalLinks": [],
  "malId": null,
  "deletedAt": null,
  "authors": [
    "Man Wang",
    "zhttty"
  ],
  "Pages": {}
}