{
  "createdAt": "2022-05-13T12:59:53.004Z",
  "updatedAt": "2022-05-13T12:59:53.004Z",
  "checkedAt": null,
  "id": 89269,
  "type": "manga",
  "title": "Shuuen Sekai no Rebellion",
  "altTitle": [
    "The Closed World's Rebellion",
    "終焉世界の天災姫〈レベリオン〉",
    "Shuuen Sekai no Tensai-hime",
    "The Closed World's Rebellion",
    "เจ้าหญิงรีเบลเลียนฝ่าวิกฤตโลกปิดตาย"
  ],
  "url": "https://anilist.co/manga/89269",
  "image": "https://s4.anilist.co/file/anilistcdn/media/manga/cover/medium/b89269-oqKNH1EGj5Gv.jpg",
  "category": "novel",
  "hentai": false,
  "externalLinks": [],
  "malId": 61549,
  "deletedAt": null,
  "authors": [
    "Takuya Fujima",
    "Ryuji Minokami"
  ],
  "Pages": {}
}