{
  "createdAt": "2022-05-13T13:03:44.784Z",
  "updatedAt": "2022-09-15T01:41:58.000Z",
  "checkedAt": "2022-09-15T01:41:58.000Z",
  "id": 99295,
  "type": "manga",
  "title": "Macho Gourmet",
  "altTitle": [
    "マッチョグルメ",
    "Maccho Gurume"
  ],
  "url": "https://anilist.co/manga/99295",
  "image": "https://s4.anilist.co/file/anilistcdn/media/manga/cover/medium/nx99295-QhUpd2bsfOxh.jpg",
  "category": "manga",
  "hentai": false,
  "externalLinks": [],
  "malId": 104299,
  "deletedAt": null,
  "authors": [
    "Nariaki Narita"
  ],
  "Pages": {}
}